labbox_ephys_widgets_jp/__init__.py
labbox_ephys_widgets_jp/_version.py
labbox_ephys_widgets_jp/create_workspace_view.py
labbox_ephys_widgets_jp/example.py
labbox_ephys_widgets_jp/labextension/package.json
labbox_ephys_widgets_jp/labextension/static/1081.8ed4b40e6cb739af8a1f.js
labbox_ephys_widgets_jp/labextension/static/1193.dfdb532cdbcc49962755.js
labbox_ephys_widgets_jp/labextension/static/1193.dfdb532cdbcc49962755.js.LICENSE.txt
labbox_ephys_widgets_jp/labextension/static/1353.88462854cd6f277e1795.js
labbox_ephys_widgets_jp/labextension/static/1436.7362f04d7f9aca5a9c36.js
labbox_ephys_widgets_jp/labextension/static/1436.7362f04d7f9aca5a9c36.js.LICENSE.txt
labbox_ephys_widgets_jp/labextension/static/1528.0a8e7b929cd3e1e13543.js
labbox_ephys_widgets_jp/labextension/static/1528.3805d8ba612b76f9c5e8.js
labbox_ephys_widgets_jp/labextension/static/1528.ff1f62e52a30fd326f2b.js
labbox_ephys_widgets_jp/labextension/static/1624.80314813833984518566.js
labbox_ephys_widgets_jp/labextension/static/1870.ae00cedcf6edf7fb032a.js
labbox_ephys_widgets_jp/labextension/static/1945.3de0fbe12fdcbe2f89ec.js
labbox_ephys_widgets_jp/labextension/static/1945.4529e6465a551ffd0464.js
labbox_ephys_widgets_jp/labextension/static/1945.5f72f64b52dbd89cfe34.js
labbox_ephys_widgets_jp/labextension/static/1945.7f5119fc7a343f4acf4f.js
labbox_ephys_widgets_jp/labextension/static/1945.c87669dc1a87e608051e.js
labbox_ephys_widgets_jp/labextension/static/1945.d6cd40b1f0f42a0036f5.js
labbox_ephys_widgets_jp/labextension/static/1945.dff108b42901171afcc6.js
labbox_ephys_widgets_jp/labextension/static/1991.ed5884975fed95b05335.js
labbox_ephys_widgets_jp/labextension/static/2263.13edf24977cb3be1e6c1.js
labbox_ephys_widgets_jp/labextension/static/2263.b2f0f7daf8382767b4af.js
labbox_ephys_widgets_jp/labextension/static/239.951c496d75af4fed512b.js
labbox_ephys_widgets_jp/labextension/static/2736.4e6701a2f15014821891.js
labbox_ephys_widgets_jp/labextension/static/2831.263bf04376cd9ee6e74b.js
labbox_ephys_widgets_jp-0.1.10.dist-info/METADATA
labbox_ephys_widgets_jp-0.1.10.dist-info/WHEEL
labbox_ephys_widgets_jp-0.1.10.dist-info/top_level.txt
labbox_ephys_widgets_jp-0.1.10.dist-info/RECORD
