Metadata-Version: 2.1
Name: labbox-ephys-widgets-jp
Version: 0.1.10
Summary: None
Home-page: https://github.com/flatironinstitute/labbox-ephys-widgets-jp
Author: Jeremy Magland and Jeff Soules
Author-email: jmagland@flatironinstitute.org
License: UNKNOWN
Keywords: ipython,jupyter,widgets
Platform: UNKNOWN
Classifier: Development Status :: 4 - Beta
Classifier: Framework :: IPython
Classifier: Intended Audience :: Developers
Classifier: Intended Audience :: Science/Research
Classifier: Topic :: Multimedia :: Graphics
Classifier: Programming Language :: Python :: 3.6
Classifier: Programming Language :: Python :: 3.7
Classifier: Programming Language :: Python :: 3.8
Classifier: Programming Language :: Python :: 3.9
Requires-Dist: ipywidgets (>=7.6.0)
Requires-Dist: labbox-ephys (>=0.6.0)
Requires-Dist: labbox (>=0.1.35)
